gitingestmcp/__init__.py
gitingestmcp/py.typed
gitingestmcp/server.py
gitingestmcp-0.1.5.dist-info/METADATA
gitingestmcp-0.1.5.dist-info/WHEEL
gitingestmcp-0.1.5.dist-info/entry_points.txt
gitingestmcp-0.1.5.dist-info/licenses/LICENSE
gitingestmcp-0.1.5.dist-info/RECORD
